ames_model/VERSION
ames_model/__init__.py
ames_model/config.yml
ames_model/pipeline.py
ames_model/predict.py
ames_model/train.py
ames_model/config/__init__.py
ames_model/config/core.py
ames_model/data/__init__.py
ames_model/data/test.csv
ames_model/data/train.csv
ames_model/processing/__init__.py
ames_model/processing/data_manager.py
ames_model/processing/feateng.py
ames_model/processing/validation.py
ames_model/trained/__init__.py
ames_model/trained/ames_model_output_v0.0.1.pkl
ames_model-0.0.1.dist-info/METADATA
ames_model-0.0.1.dist-info/WHEEL
ames_model-0.0.1.dist-info/top_level.txt
ames_model-0.0.1.dist-info/RECORD
